boltz_client.py
libboltz_client.so
boltz_client-0.3.0.post1.dist-info/METADATA
boltz_client-0.3.0.post1.dist-info/WHEEL
boltz_client-0.3.0.post1.dist-info/RECORD
