Metadata-Version: 2.4
Name: boltz_client
Version: 0.3.0.post1
Summary: Boltz Swap library
Requires-Python: >=3.10
